{
    "camera_data": {
        "width": 500,
        "height": 500,
        "camera_look_at": {
            "at": [
                -0.0,
                1.0,
                -7.549790126404332e-08
            ],
            "eye": [
                -0.0,
                10.0,
                -0.0
            ],
            "up": [
                1.0,
                0.0,
                0.0
            ]
        },
        "intrinsics": {
            "fx": 603.5535070631239,
            "fy": 603.5535070631239,
            "cx": 0.0,
            "cy": 0.0
        }
    },
    "objects": [
        {
            "class": "obj_000001",
            "name": "obj_000001_000",
            "visibility": 5413,
            "projected_cuboid": [
                [
                    313.066984597863,
                    330.31758585813793
                ],
                [
                    266.99915532736253,
                    336.88592254704616
                ],
                [
                    210.4066706058401,
                    360.0418901368922
                ],
                [
                    253.424603550592,
                    355.6936459449342
                ],
                [
                    338.576097223161,
                    410.1931294123074
                ],
                [
                    289.8010921857601,
                    408.86349833821276
                ],
                [
                    234.59656612903464,
                    437.23038304567217
                ],
                [
                    280.68791928730144,
                    442.0378277675394
                ],
                [
                    273.2128582413023,
                    384.617235799834
                ]
            ],
            "location": [
                0.5551484182976409,
                -2.782034548507156,
                -12.00000021003777
            ],
            "quaternion_xyzw": [
                0.5798598953669106,
                0.423280067602116,
                0.22113985651307685,
                -0.6600709431395962
            ]
        },
        {
            "class": "obj_000002",
            "name": "obj_000002_001",
            "visibility": 440,
            "projected_cuboid": [
                [
                    424.21254145532833,
                    42.67944970252816
                ],
                [
                    404.4212475947428,
                    47.931854364674564
                ],
                [
                    405.89309968544535,
                    50.58320369463863
                ],
                [
                    425.6737121422036,
                    45.42655471492799
                ],
                [
                    453.0934619076588,
                    -2.4421130205362545
                ],
                [
                    433.34770010251106,
                    3.862762442609011
                ],
                [
                    434.6798211067244,
                    6.513335262896732
                ],
                [
                    454.41142726913404,
                    0.3026923329910005
                ],
                [
                    429.64901496794187,
                    23.89558550192524
                ]
            ],
            "location": [
                3.5879858588240534,
                4.455464092797062,
                -11.999999663621812
            ],
            "quaternion_xyzw": [
                0.3893133982953459,
                -0.39645347411839055,
                0.1657178138147146,
                0.8147375816492437
            ]
        },
        {
            "class": "obj_000003",
            "name": "obj_000003_002",
            "visibility": 1865,
            "projected_cuboid": [
                [
                    27.745574701803207,
                    159.2083132274588
                ],
                [
                    -59.900800335733436,
                    125.61103891112722
                ],
                [
                    -24.191682126100545,
                    118.2026084345191
                ],
                [
                    52.16171074175463,
                    147.84799434682614
                ],
                [
                    39.10755578506769,
                    122.08158740758945
                ],
                [
                    -49.82732869164187,
                    87.11391555394411
                ],
                [
                    -14.83958290467649,
                    84.43027660059519
                ],
                [
                    62.487341030157694,
                    115.13210241416684
                ],
                [
                    5.426976278741904,
                    120.01764060479846
                ]
            ],
            "location": [
                -4.8527203635496114,
                2.574400619265354,
                -11.999999805638156
            ],
            "quaternion_xyzw": [
                0.7863892789376768,
                -0.1018064032632062,
                -0.16471244918420466,
                0.5865979605404614
            ]
        },
        {
            "class": "obj_000004",
            "name": "obj_000004_003",
            "visibility": 3902,
            "projected_cuboid": [
                [
                    271.4271138264957,
                    276.9467757657955
                ],
                [
                    246.3101516306379,
                    328.3586032355891
                ],
                [
                    182.8871714506824,
                    306.62412520733335
                ],
                [
                    205.39377743592343,
                    253.15759275803111
                ],
                [
                    272.4944571216678,
                    303.59914665698335
                ],
                [
                    245.4513386933839,
                    357.53748399999813
                ],
                [
                    177.18610640072166,
                    334.7281241553408
                ],
                [
                    201.1947126016094,
                    278.46110659633007
                ],
                [
                    225.3621950273272,
                    305.1902465527972
                ]
            ],
            "location": [
                -0.47991380569441855,
                -1.1072469584815252,
                -12.000000083594822
            ],
            "quaternion_xyzw": [
                0.8066992500810818,
                0.5415568156738421,
                0.13702824707303168,
                -0.19281025600293925
            ]
        },
        {
            "class": "obj_000005",
            "name": "obj_000005_004",
            "visibility": 4389,
            "projected_cuboid": [
                [
                    251.40890797802092,
                    34.527779458811494
                ],
                [
                    214.56424615792608,
                    22.421750209175144
                ],
                [
                    274.0250321535467,
                    -21.135357252609538
                ],
                [
                    311.7951249719348,
                    -5.203350007217637
                ],
                [
                    259.87841666807685,
                    119.85501734762687
                ],
                [
                    222.71808574076223,
                    112.08570732904363
                ],
                [
                    284.59732001227025,
                    78.70063125526411
                ],
                [
                    322.60281094371055,
                    89.28977882780353
                ],
                [
                    266.43346058054846,
                    54.52503280405443
                ]
            ],
            "location": [
                0.33667524695322637,
                3.8765408871490705,
                -11.999999707329298
            ],
            "quaternion_xyzw": [
                0.7159788811618214,
                -0.2310916860853038,
                -0.2601929297088684,
                -0.6052028698560765
            ]
        },
        {
            "class": "obj_000006",
            "name": "obj_000006_005",
            "visibility": 1483,
            "projected_cuboid": [
                [
                    104.16526078361622,
                    57.39492578352554
                ],
                [
                    130.11852392942373,
                    78.5332580302344
                ],
                [
                    113.38867424142896,
                    95.66252010969743
                ],
                [
                    84.72768515148908,
                    72.79697978594689
                ],
                [
                    135.31315829712975,
                    12.646447497766303
                ],
                [
                    161.88622438327826,
                    35.312486255050146
                ],
                [
                    147.4807640362494,
                    49.02362479838308
                ],
                [
                    118.0516788972705,
                    24.344333275596767
                ],
                [
                    124.53479412131563,
                    53.45823909656173
                ]
            ],
            "location": [
                -2.484589459402046,
                3.897751422710127,
                -11.999999705727948
            ],
            "quaternion_xyzw": [
                0.2050977400648271,
                0.8222494011180941,
                -0.45295492476902444,
                -0.2768983125783217
            ]
        },
        {
            "class": "obj_000007",
            "name": "obj_000007_006",
            "visibility": 1929,
            "projected_cuboid": [
                [
                    97.12840017452018,
                    386.6295785549315
                ],
                [
                    139.56690731882884,
                    395.23995897885936
                ],
                [
                    172.16760959312725,
                    391.8418783227848
                ],
                [
                    130.50215158986742,
                    383.91421733550635
                ],
                [
                    92.29461317292714,
                    435.2412695598414
                ],
                [
                    134.7890035220936,
                    446.816923263113
                ],
                [
                    167.93492452647706,
                    440.18089964641115
                ],
                [
                    126.19359915509216,
                    429.6390676600689
                ],
                [
                    132.5109106508665,
                    413.3895438618581
                ]
            ],
            "location": [
                -2.3260059570392952,
                -3.258491999010923,
                -12.000000246009307
            ],
            "quaternion_xyzw": [
                -0.1947693319891438,
                0.7142880423157123,
                0.6330053201105299,
                0.22618966517737488
            ]
        },
        {
            "class": "obj_000008",
            "name": "obj_000008_007",
            "visibility": 3968,
            "projected_cuboid": [
                [
                    419.986598348052,
                    460.38655127087054
                ],
                [
                    455.3683315774727,
                    361.3176854021369
                ],
                [
                    455.8453995485155,
                    378.2318716801643
                ],
                [
                    422.1007179702399,
                    474.3547876912163
                ],
                [
                    535.8808060405576,
                    505.29543081890915
                ],
                [
                    563.4983134829855,
                    393.4984398642853
                ],
                [
                    559.1757089896864,
                    410.36497188934777
                ],
                [
                    532.4920854705729,
                    518.3197686867475
                ],
                [
                    491.42261454565124,
                    434.71397717778035
                ]
            ],
            "location": [
                4.809964899880583,
                -3.6824696665250936,
                -12.000000278018732
            ],
            "quaternion_xyzw": [
                -0.3144600514010181,
                0.8030391893435884,
                0.2931584088934748,
                -0.4126755187145294
            ]
        },
        {
            "class": "obj_000009",
            "name": "obj_000009_008",
            "visibility": 1773,
            "projected_cuboid": [
                [
                    93.05279010865999,
                    378.06958077787004
                ],
                [
                    44.42918518561737,
                    404.0264242540595
                ],
                [
                    61.27161260933124,
                    427.9373000255317
                ],
                [
                    111.25307481350507,
                    399.7742328071872
                ],
                [
                    100.58633258253221,
                    407.0771932414033
                ],
                [
                    54.169140255807605,
                    433.2879290320525
                ],
                [
                    70.75789894827608,
                    457.51368622132895
                ],
                [
                    118.3992133624244,
                    429.1576575222195
                ],
                [
                    82.1699359232012,
                    416.848801943814
                ]
            ],
            "location": [
                -3.326897663245173,
                -3.327269870274382,
                -12.000000251201893
            ],
            "quaternion_xyzw": [
                -0.4521382739986458,
                0.14055837383814065,
                0.30432019226737833,
                0.8265612774064891
            ]
        }
    ]
}